{
    "key": "group_5d84582d0d320",
    "title": "Downloads & links",
    "fields": [
        {
            "key": "field_5d845848455c7",
            "label": "Download",
            "name": "download",
            "type": "file",
            "instructions": "",
            "required": 0,
            "conditional_logic": 0,
            "wrapper": {
                "width": "50",
                "class": "",
                "id": ""
            },
            "return_format": "array",
            "library": "all",
            "min_size": "",
            "max_size": "",
            "mime_types": ""
        },
        {
            "key": "field_5d84588c455ca",
            "label": "URL",
            "name": "url",
            "type": "url",
            "instructions": "",
            "required": 0,
            "conditional_logic": 0,
            "wrapper": {
                "width": "50",
                "class": "",
                "id": ""
            },
            "default_value": "",
            "placeholder": ""
        }
    ],
    "location": [
        [
            {
                "param": "post_type",
                "operator": "==",
                "value": "publication"
            }
        ],
        [
            {
                "param": "post_type",
                "operator": "==",
                "value": "case"
            }
        ],
        [
            {
                "param": "post_type",
                "operator": "==",
                "value": "post"
            }
        ]
    ],
    "menu_order": 0,
    "position": "normal",
    "style": "default",
    "label_placement": "top",
    "instruction_placement": "label",
    "hide_on_screen": "",
    "active": 1,
    "description": "",
    "modified": 1585776264
}